deepnone.py
deepnone-0.2.0.dist-info/WHEEL
deepnone-0.2.0.dist-info/METADATA
deepnone-0.2.0.dist-info/RECORD
