Metadata-Version: 2.1
Name: deepnone
Version: 0.2.0
Summary: Deeply accees optional fields, without all the none-checks
Author: Jack Reilly
Author-email: jackdreilly@gmail.com
Requires-Python: >=3.8,<4.0
Classifier: Programming Language :: Python :: 3
Classifier: Programming Language :: Python :: 3.10
Classifier: Programming Language :: Python :: 3.8
Classifier: Programming Language :: Python :: 3.9
